{
    "threeDModel": "FemaleFace8",
    "gender": "",
    "age": "",
    "features": [
        {
            "id": "Alar_Crest/Alar_Curvature/Alar_Base_Junction/Alar-Facial_Groove/Alar-Cheek_Junction/Alar_Crease_left",
            "name": "Alar Base Junction/Alar Crease - left",
            "abbrv": "ac_l",
            "list": "Y",
            "imageFile": "feature_point_alar_crest_left-basal.png",
            "description": "The junction between the left alar crease and the cheek.",
            "references": "(10)",
            "usedInMeasurements": [
                "Ala/Alar_Length_(left)",
                "Ala/Alar_Length_(left)_Surface",
                "Alar_Base_Width",
                "Alar_Base_Width_Surface",
                "Premaxilla_-_left",
                "Premaxilla_-_left_Surface",
                "Lobule_-_Base_Ratio",
                "Nasal_Tip_Projection:_Byrd_and_Hobar",
                "Nasal_Tip_Projection:_Goode"
            ],
            "xVal": 15.36,
            "yVal": -31.38,
            "zVal": 95.23,
            "cameraX": "",
            "cameraY": "",
            "cameraZ": "",
            "type": "Points"
        },
        {
            "id": "Alar_Crest/Alar_Curvature/Alar_Base_Junction/Alar-Facial_Groove/Alar-Cheek_Junction/Alar_Crease_right",
            "name": "Alar Base Junction/Alar Crease - right",
            "abbrv": "ac_r",
            "list": "Y",
            "imageFile": "feature_point_alar_crest_right-basal.png",
            "description": "The junction between the right alar crease and the cheek.",
            "references": "(10)",
            "usedInMeasurements": [
                "Ala/Alar_Length_(right)",
                "Alar_Base_Width",
                "Alar_Base_Width_Surface",
                "Premaxilla_-_right",
                "Premaxilla_-_right_Surface",
                "Lobule_-_Base_Ratio"
            ],
            "xVal": -15.68,
            "yVal": -32.35,
            "zVal": 94.29,
            "cameraX": "",
            "cameraY": "",
            "cameraZ": "",
            "type": "Points"
        },
        {
            "id": "Alar_Ridge's_Highest_Point_left",
            "name": "Alar Rim’s Highest Point - left",
            "abbrv": "armax_l",
            "list": "Y",
            "imageFile": "feature_point_alar_rim_highest_point_left-lateral.png",
            "description": "The highest point of the left alar rim.",
            "references": "(10, 11)",
            "usedInMeasurements": [
                "Columella-Alar_Distance_-_left",
                "Columella-Alar_Distance_-_left_Surface"
            ],
            "xVal": 11.61,
            "yVal": -25.99,
            "zVal": 99.48,
            "cameraX": "",
            "cameraY": "",
            "cameraZ": "",
            "type": "Points"
        },
        {
            "id": "Alar_Ridge's_Highest_Point_right",
            "name": "Alar Rim’s Highest Point - right",
            "abbrv": "armax_r",
            "list": "Y",
            "imageFile": "feature_point_alar_rim_highest_point_right-lateral.png",
            "description": "The highest point of the right alar rim.",
            "references": "(10, 11)",
            "usedInMeasurements": [
                "Columella-Alar_Distance_-_right",
                "Columella-Alar_Distance_-_right_Surface"
            ],
            "xVal": -10.21,
            "yVal": -26.08,
            "zVal": 99.64,
            "cameraX": "",
            "cameraY": "",
            "cameraZ": "",
            "type": "Points"
        },
        {
            "id": "Alare/Alar_Flare_left",
            "name": "Alare/Alar Flare - left",
            "abbrv": "al_l",
            "list": "Y",
            "imageFile": "feature_point_alare_alar_flare_left-frontal.png",
            "description": "The most lateral point on the left ala of the nose.",
            "references": "(10)",
            "usedInMeasurements": [
                "Interalar_Distance",
                "Interalar_Distance_Surface",
                "Interalar_Angle",
                "Nasal_Width–Intercanthal_Distance_Ratio",
                "Nasal_Width-Length_Ratio"
            ],
            "xVal": 14.3,
            "yVal": -26.11,
            "zVal": 97.71,
            "cameraX": "",
            "cameraY": "",
            "cameraZ": "",
            "type": "Points"
        },
        {
            "id": "Alare/Alar_Flare_right",
            "name": "Alare/Alar Flare - right",
            "abbrv": "al_r",
            "list": "Y",
            "imageFile": "feature_point_alare_alar_flare_right-frontal.png",
            "description": "The most lateral point on the right ala of the nose.",
            "references": "(10)",
            "usedInMeasurements": [
                "Interalar_Distance",
                "Interalar_Distance_Surface",
                "Interalar_Angle",
                "Nasal_Width–Intercanthal_Distance_Ratio",
                "Nasal_Width-Length_Ratio"
            ],
            "xVal": -12.79,
            "yVal": -26.15,
            "zVal": 98.06,
            "cameraX": "",
            "cameraY": "",
            "cameraZ": "",
            "type": "Points"
        },
        {
            "id": "Anterior/Superior_Point_of_Nostril/Columella_Point_left",
            "name": "Anterior Point of Nostril/Columella Junction left",
            "abbrv": "stn_l",
            "list": "Y",
            "imageFile": "feature_point_anterior_point_of_the_nostril_left-basal.png",
            "description": "The point where the left ala meets the upper end of the columella.",
            "references": "(12)",
            "usedInMeasurements": [
                "Interaxial_Angle_(Nostril_Inclination)"
            ],
            "xVal": 8.58,
            "yVal": -27.71,
            "zVal": 99.46,
            "cameraX": "",
            "cameraY": "",
            "cameraZ": "",
            "type": "Points"
        },
        {
            "id": "Anterior/Superior_Point_of_Nostril/Columella_Point_right",
            "name": "Anterior Point of Nostril/Columella Junction right",
            "abbrv": "stn_r",
            "list": "Y",
            "imageFile": "feature_point_anterior_point_of_the_nostril_right-basal.png",
            "description": "The point where the right ala meets the upper end of the columella.",
            "references": "(12)",
            "usedInMeasurements": [
                "Interaxial_Angle_(Nostril_Inclination)"
            ],
            "xVal": -6.97,
            "yVal": -27.8,
            "zVal": 99.56,
            "cameraX": "",
            "cameraY": "",
            "cameraZ": "",
            "type": "Points"
        },
        {
            "id": "Columellar_Break_Point",
            "name": "Columellar Break Point",
            "abbrv": "cb",
            "list": "Y",
            "imageFile": "feature_point_columellar_break_point-lateral(l).png",
            "description": "The point in the columellar region of the nose where the tip of the nose stops curving and the columellar linear structure begins, in the midline.",
            "references": "(15, 16)",
            "usedInMeasurements": [
                "Columella_Length",
                "Columella_Length_Surface",
                "Infratip_Lobule/Infralobule",
                "Infratip_Lobule/Infralobule_Surface",
                "Columellar_Labial_Angle",
                "Columellar_Lobular_Angle"
            ],
            "xVal": -0.52,
            "yVal": -28.46,
            "zVal": 101.7,
            "cameraX": "",
            "cameraY": "",
            "cameraZ": "",
            "type": "Points"
        },
        {
            "id": "Columella's_Lowest_Point_left",
            "name": "Columellar Rim - left",
            "abbrv": "cmin_l",
            "list": "Y",
            "imageFile": "feature_point_left_columellar_rim-lateral(l).png",
            "description": "Lowest point (or widest point) of left nostril as seen from the lateral view on the columellar side at the mucocutaneous junction.",
            "references": "(11)",
            "usedInMeasurements": [
                "Columella-Alar_Distance_-_left",
                "Columella-Alar_Distance_-_left_Surface"
            ],
            "xVal": 3.56,
            "yVal": -30.24,
            "zVal": 99.28,
            "cameraX": "",
            "cameraY": "",
            "cameraZ": "",
            "type": "Points"
        },
        {
            "id": "Columella's_Lowest_Point_right",
            "name": "Columellar Rim - right",
            "abbrv": "cmin_r",
            "list": "Y",
            "imageFile": "feature_point_right_columellar_rim-lateral(l).png",
            "description": "Lowest point (or widest point) of right nostril as seen from the lateral view on the columellar side at the mucocutaneous junction.",
            "references": "(11)",
            "usedInMeasurements": [
                "Columella-Alar_Distance_-_right",
                "Columella-Alar_Distance_-_right_Surface"
            ],
            "xVal": -4.75,
            "yVal": -30.65,
            "zVal": 97.74,
            "cameraX": "",
            "cameraY": "",
            "cameraZ": "",
            "type": "Points"
        },
        {
            "id": "Crista_Philtri_left",
            "name": "Crista Philtri - left",
            "abbrv": "cph_l",
            "list": "Y",
            "imageFile": "feature_point_crista_philtri_left-basal.png",
            "description": "The point on the crest of the left philtrum ridge, the vertical groove in the median portion of the upper lip, just above the vermilion border.",
            "references": "(17)",
            "usedInMeasurements": [
                "Philtrum_Width/Interphiltral_Distance",
                "Philtrum_Width/Interphiltral_Distance_Surface"
            ],
            "xVal": 6.57,
            "yVal": -28.71,
            "zVal": 99.37,
            "cameraX": "",
            "cameraY": "",
            "cameraZ": "",
            "type": "Points"
        },
        {
            "id": "Crista_Philtri_right",
            "name": "Crista Philtri - right",
            "abbrv": "cph_r",
            "list": "Y",
            "imageFile": "feature_point_crista_philtri_right-basal.png",
            "description": "The point on the crest of the right philtrum ridge, the vertical groove in the median portion of the upper lip, just above the vermilion border.",
            "references": "(17)",
            "usedInMeasurements": [
                "Philtrum_Width/Interphiltral_Distance",
                "Philtrum_Width/Interphiltral_Distance_Surface"
            ],
            "xVal": -4.3,
            "yVal": -48.66,
            "zVal": 98.62,
            "cameraX": "",
            "cameraY": "",
            "cameraZ": "",
            "type": "Points"
        },
        {
            "id": "Endocanthion/Medial_Canthus_left",
            "name": "Endocanthion/Medial Canthus - left",
            "abbrv": "en_l",
            "list": "Y",
            "imageFile": "feature_point_endocanthion_left-frontal.png",
            "description": "The inner corner of the left eye where the upper and lower eyelids meet.",
            "references": "(18, 19)",
            "usedInMeasurements": [
                "(Inner)_Intercanthal_Distance/Width",
                "(Inner)_Intercanthal_Distance/Width_Surface",
                "Left_Eye_Width",
                "Left_Eye_Width_Surface",
                "Nasal_Width–Intercanthal_Distance_Ratio"
            ],
            "xVal": 6.86,
            "yVal": -47.43,
            "zVal": 97.89,
            "cameraX": "",
            "cameraY": "",
            "cameraZ": "",
            "type": "Points"
        },
        {
            "id": "Endocanthion/Medial_Canthus_right",
            "name": "Endocanthion/Medial Canthus - right",
            "abbrv": "en_r",
            "list": "Y",
            "imageFile": "feature_point_endocanthion_right-frontal.png",
            "description": "The inner corner of the right eye where the upper and lower eyelids meet.",
            "references": "(18, 19)",
            "usedInMeasurements": [
                "(Inner)_Intercanthal_Distance/Width",
                "(Inner)_Intercanthal_Distance/Width_Surface",
                "Right_Eye_Width",
                "Right_Eye_Width_Surface",
                "Nasal_Width–Intercanthal_Distance_Ratio"
            ],
            "xVal": -21.05,
            "yVal": 14,
            "zVal": 77.05,
            "cameraX": "",
            "cameraY": "",
            "cameraZ": "",
            "type": "Points"
        },
        {
            "id": "Exocanthion/Lateral_Canthus_left",
            "name": "Exocanthion/Lateral Canthus - left",
            "abbrv": "ex_l",
            "list": "Y",
            "imageFile": "feature_point_exocanthion_left-frontal.png",
            "description": "The outer corner of the left eye where the upper and lower eyelids meet.",
            "references": "(18, 19)",
            "usedInMeasurements": [
                "Left_Eye_Width",
                "Left_Eye_Width_Surface",
                "Outer_Intercanthal_Distance",
                "Outer_Intercanthal_Distance_Surface"
            ],
            "xVal": 21.42,
            "yVal": 14.46,
            "zVal": 77.2,
            "cameraX": "",
            "cameraY": "",
            "cameraZ": "",
            "type": "Points"
        },
        {
            "id": "Exocanthion/Lateral_Canthus_right",
            "name": "Exocanthion/Lateral Canthus - right",
            "abbrv": "ex_r",
            "list": "Y",
            "imageFile": "feature_point_exocanthion_right-frontal.png",
            "description": "The outer corner of the right eye where the upper and lower eyelids meet.",
            "references": "(18,19)",
            "usedInMeasurements": [
                "Outer_Intercanthal_Distance",
                "Outer_Intercanthal_Distance_Surface",
                "Right_Eye_Width",
                "Right_Eye_Width_Surface"
            ],
            "xVal": -55.57,
            "yVal": 16.52,
            "zVal": 66.46,
            "cameraX": "",
            "cameraY": "",
            "cameraZ": "",
            "type": "Points"
        },
        {
            "id": "Glabella",
            "name": "Glabella",
            "abbrv": "g",
            "list": "Y",
            "imageFile": "feature_point_glabella-lateral(l).png",
            "description": "The most prominent point of the forehead in the midline between the eyebrows.",
            "references": "(20)",
            "usedInMeasurements": [
                "Mid-Facial_Height",
                "Mid-Facial_Height_Surface",
                "Upper_Facial_Height",
                "Nasofrontal_Angle",
                "Nasolabial_Angle_IV",
                "Total_Facial_Convexity_Angle"
            ],
            "xVal": -0.99,
            "yVal": 46.92,
            "zVal": 80.5,
            "cameraX": "",
            "cameraY": "",
            "cameraZ": "",
            "type": "Points"
        },
        {
            "id": "Maxilloanteriorale_left",
            "name": "Maxilloanteriorale - left",
            "abbrv": "ma_l",
            "list": "Y",
            "imageFile": "feature_point_maxilloanteriorale_left-frontal.png",
            "description": "The point where the left maxilloanterioral and nasoanterioral sutures meet",
            "references": "(9, 25, 26)",
            "usedInMeasurements": [
                "Nasal_Root_Width",
                "Nasal_Root_Width_Surface"
            ],
            "xVal": 13.5,
            "yVal": -4.83,
            "zVal": 87.73,
            "cameraX": "",
            "cameraY": "",
            "cameraZ": "",
            "type": "Points"
        },
        {
            "id": "Maxilloanteriorale_right",
            "name": "Maxilloanteriorale - right",
            "abbrv": "ma_r",
            "list": "Y",
            "imageFile": "feature_point_maxilloanteriorale_right-frontal.png",
            "description": "The point where the right maxilloanterioral and nasoanterioral sutures meet",
            "references": "(9, 25, 26)",
            "usedInMeasurements": [
                "Nasal_Root_Width",
                "Nasal_Root_Width_Surface"
            ],
            "xVal": -10.48,
            "yVal": -4.12,
            "zVal": 88.59,
            "cameraX": "",
            "cameraY": "",
            "cameraZ": "",
            "type": "Points"
        },
        {
            "id": "Maxillofrontale_left",
            "name": "Maxillofrontale - left",
            "abbrv": "mf_l",
            "list": "Y",
            "imageFile": "feature_point_maxillofrontale_left-frontal.png",
            "description": "The soft tissue point located at the left lateral margin of the base of the nasal root at the level of the endocanthion.",
            "references": "(33)",
            "usedInMeasurements": [
                "Nasal_Root_Width",
                "Dorsal_aesthetic_line_width_at_intercanthal_distance_to_interphiltral_width_ratio"
            ],
            "xVal": 11.11,
            "yVal": 15.08,
            "zVal": 79.92,
            "cameraX": "",
            "cameraY": "",
            "cameraZ": "",
            "type": "Points"
        },
        {
            "id": "Maxillofrontale_right",
            "name": "Maxillofrontale - right",
            "abbrv": "mf_r",
            "list": "Y",
            "imageFile": "feature_point_maxillofrontale_right-frontal.png",
            "description": "The soft tissue point located at the right lateral margin of the base of the nasal root at the level of the endocanthion.",
            "references": "(33)",
            "usedInMeasurements": [
                "Nasal_Root_Width",
                "Dorsal_aesthetic_line_width_at_intercanthal_distance_to_interphiltral_width_ratio"
            ],
            "xVal": -9.89,
            "yVal": 17.24,
            "zVal": 79.28,
            "cameraX": "",
            "cameraY": "",
            "cameraZ": "",
            "type": "Points"
        },
        {
            "id": "Menton/Gnathion",
            "name": "Menton/Gnathion",
            "abbrv": "me",
            "list": "Y",
            "imageFile": "feature_point_menton-lateral(l).png",
            "description": "Lowest point on the soft tissue proﬁle of the chin in mid-sagittal plane.",
            "references": "(18, 27)",
            "usedInMeasurements": [
                "Face_Length/Height",
                "Face_Length/Height_Surface",
                "Height_of_the_Mandible/Chin_Height",
                "Height_of_the_Mandible/Chin_Height_Surface",
                "Lower_Facial_Height",
                "Lower_Facial_Height_Surface",
                "Mentocervical_Angle",
                "Nasal_Tip_Projection:_Crumley_and_Lanser_II"
            ],
            "xVal": 0.74,
            "yVal": -106.87,
            "zVal": 87.89,
            "cameraX": "",
            "cameraY": "",
            "cameraZ": "",
            "type": "Points"
        },
        {
            "id": "Nasal_Parenthesis_left",
            "name": "Nasal Parenthesis - left",
            "abbrv": "np_l",
            "list": "Y",
            "imageFile": "feature_point_nasal_parenthesis_left-frontal.png",
            "description": "The summit of the left nasal parentheses/canthal-alar line.",
            "references": "(30)",
            "usedInMeasurements": [
                "Base_Bony_Width_Surface",
                "Base_Bony_Width"
            ],
            "xVal": 14.13,
            "yVal": -5.26,
            "zVal": 87.56,
            "cameraX": "",
            "cameraY": "",
            "cameraZ": "",
            "type": "Points"
        },
        {
            "id": "Nasal_Parenthesis_right",
            "name": "Nasal Parenthesis - right",
            "abbrv": "np_r",
            "list": "Y",
            "imageFile": "feature_point_nasal_parenthesis_right-frontal.png",
            "description": "The summit of the right nasal parentheses/canthal-alar line.",
            "references": "(30)",
            "usedInMeasurements": [
                "Base_Bony_Width_Surface",
                "Base_Bony_Width"
            ],
            "xVal": -16.62,
            "yVal": -4.91,
            "zVal": 85.44,
            "cameraX": "",
            "cameraY": "",
            "cameraZ": "",
            "type": "Points"
        },
        {
            "id": "Nasion/Radix",
            "name": "Nasion/Radix",
            "abbrv": "n",
            "list": "Y",
            "imageFile": "feature_point_nasion-lateral(l).png",
            "description": "The midpoint of the nasofrontal suture line where the frontal bone and nasal bones join.",
            "references": "(22)",
            "usedInMeasurements": [
                "Nasal_Bridge_Length",
                "Nasal_Bridge_Length_Surface",
                "Nose_Height",
                "Nose_Height_Surface",
                "Radix_Depth",
                "Radix_Depth_Surface",
                "Degree_of_Deviation_(C-type)",
                "Degree_of_Deviation_(I-type)",
                "Nasal_Tip_Angle",
                "Nasofacial_Angle",
                "Nasofrontal_Angle",
                "Nasomental_Angle",
                "Nasal_Tip_Projection:_Baum",
                "Nasal_Tip_Projection:_Byrd_and_Hobar",
                "Nasal_Tip_Projection:_Crumley_and_Lanser_I",
                "Nasal_Tip_Projection:_Crumley_and_Lanser_II",
                "Nasal_Tip_Projection:_Goode",
                "Nasal_Tip_Projection:_Powell_and_Humphries",
                "Nasal_Width-Length_Ratio"
            ],
            "xVal": 1.49,
            "yVal": 26.19,
            "zVal": 80.34,
            "cameraX": "",
            "cameraY": "",
            "cameraZ": "",
            "type": "Points"
        },
        {
            "id": "Pogonion",
            "name": "Pogonion",
            "abbrv": "pg",
            "list": "Y",
            "imageFile": "feature_point_pogonion-lateral(l).png",
            "description": "Most anterior point on the soft tissue profile of the chin in mid-sagittal plane.",
            "references": "(31)",
            "usedInMeasurements": [
                "Mentocervical_Angle",
                "Nasofacial_Angle",
                "Nasolabial_Angle_IV",
                "Nasomental_Angle",
                "Total_Facial_Convexity_Angle"
            ],
            "xVal": -7.4,
            "yVal": -85.75,
            "zVal": 94.1,
            "cameraX": "",
            "cameraY": "",
            "cameraZ": "",
            "type": "Points"
        },
        {
            "id": "Posterior/Inferior_Point_of_Nostril_left",
            "name": "Posterior Point of Nostril - left",
            "abbrv": "itn_l",
            "list": "Y",
            "imageFile": "feature_point_posterior_point_of_the_nostril_left-basal.png",
            "description": "The point where the left ala meets the nostril floor at a point corresponding to sbal.",
            "references": "(12)",
            "usedInMeasurements": [
                "Interaxial_Angle_(Nostril_Inclination)",
                "Nasolabial_Angle_IV"
            ],
            "xVal": 10.33,
            "yVal": -28.06,
            "zVal": 98.47,
            "cameraX": "",
            "cameraY": "",
            "cameraZ": "",
            "type": "Points"
        },
        {
            "id": "Posterior/Inferior_Point_of_Nostril_right",
            "name": "Posterior Point of Nostril - right",
            "abbrv": "itn_r",
            "list": "Y",
            "imageFile": "feature_point_posterior_point_of_the_nostril_right-basal.png",
            "description": "The point where the right ala meets the nostril floor at a point corresponding to sbal.",
            "references": "(12)",
            "usedInMeasurements": [
                "Interaxial_Angle_(Nostril_Inclination)",
                "Nasolabial_Angle_IV"
            ],
            "xVal": -8.52,
            "yVal": -28.46,
            "zVal": 98.53,
            "cameraX": "",
            "cameraY": "",
            "cameraZ": "",
            "type": "Points"
        },
        {
            "id": "Pronasale/Tip",
            "name": "Pronasale/Tip",
            "abbrv": "prn",
            "list": "Y",
            "imageFile": "feature_point_pronasale_tip-lateral(l).png",
            "description": "The most protrusive point on the nasal tip in the midline.",
            "references": "(18)",
            "usedInMeasurements": [
                "Ala/Alar_Length_(left)",
                "Ala/Alar_Length_(right)",
                "Ala/Alar_Length_(right)_Surface",
                "Infratip_Lobule/Infralobule",
                "Infratip_Lobule/Infralobule_Surface",
                "Nasal_Bridge_Length",
                "Nasal_Bridge_Length_Surface",
                "Nasal_Tip_Projection",
                "Nasal_Tip_Projection_Surface",
                "Supratip_Lobule",
                "Supratip_Lobule_Surface",
                "Columellar_Lobular_Angle",
                "Degree_of_Deviation_(C-type)",
                "Degree_of_Deviation_(I-type)",
                "Interalar_Angle",
                "Mentocervical_Angle",
                "Nasal_Tip_Angle",
                "Nasofacial_Angle",
                "Nasofrontal_Angle",
                "Nasolabial_Angle_I",
                "Nasomental_Angle",
                "Total_Facial_Convexity_Angle",
                "Nasal_Tip_Projection:_Baum",
                "Nasal_Tip_Projection:_Byrd_and_Hobar",
                "Nasal_Tip_Projection:_Crumley_and_Lanser_I",
                "Nasal_Tip_Projection:_Crumley_and_Lanser_II",
                "Nasal_Tip_Projection:_Goode",
                "Nasal_Tip_Projection:_Powell_and_Humphries",
                "Nasal_Tip_Projection:_Simons",
                "Nasal_Width-Length_Ratio"
            ],
            "xVal": 0.46,
            "yVal": -15.85,
            "zVal": 107.8,
            "cameraX": "",
            "cameraY": "",
            "cameraZ": "",
            "type": "Points"
        },
        {
            "id": "Rhinion",
            "name": "Rhinion",
            "abbrv": "r",
            "list": "Y",
            "imageFile": "feature_point_rhinion-frontal.png",
            "description": "Osseocartilaginous junction. A craniometric point corresponding to the lower end of the suture between the two nasal bones.",
            "references": "(32)",
            "usedInMeasurements": [
                "Kyphion_Angle"
            ],
            "xVal": 2.53,
            "yVal": 4.22,
            "zVal": 87.94,
            "cameraX": "",
            "cameraY": "",
            "cameraZ": "",
            "type": "Points"
        },
        {
            "id": "Sellion",
            "name": "Sellion",
            "abbrv": "se",
            "list": "Y",
            "imageFile": "feature_point_sellion-frontal.png",
            "description": "The deepest depression of the nasal bones and often coincides with soft tissue nasion.",
            "references": "(22)",
            "usedInMeasurements": [
                "Angle_of_Sellion_left",
                "Angle_of_Sellion_right",
                "Nasal_Root_Depth/Length_Index"
            ],
            "xVal": 2.06,
            "yVal": 27.54,
            "zVal": 80.33,
            "cameraX": "",
            "cameraY": "",
            "cameraZ": "",
            "type": "Points"
        },
        {
            "id": "Sill-Base Junction_left",
            "name": "Sill-base junction - left",
            "abbrv": "sbj_l",
            "list": "Y",
            "imageFile": "feature_point_sill_base_junction_left.png",
            "description": "The point where the alar base meets the nasal sill along the nostril.",
            "references": "(10)",
            "usedInMeasurements": [
                "Distance_between_sill_base_junction_and_alar_flare",
                "Distance_between_sill_base_junction_and_alar_flare_Surface"
            ],
            "xVal": 10.62,
            "yVal": -31.72,
            "zVal": 96.21,
            "cameraX": "",
            "cameraY": "",
            "cameraZ": "",
            "type": "Points"
        },
        {
            "id": "Sill-Base Junction_right",
            "name": "Sill-base junction - right",
            "abbrv": "sbj_r",
            "list": "Y",
            "imageFile": "feature_point_sill_base_junction_left.png",
            "description": "The point where the alar base meets the nasal sill along the nostril.",
            "references": "(10)",
            "usedInMeasurements": [],
            "xVal": -10.87,
            "yVal": -30.96,
            "zVal": 96.51,
            "cameraX": "",
            "cameraY": "",
            "cameraZ": "",
            "type": "Points"
        },
        {
            "id": "Stomion",
            "name": "Stomion",
            "abbrv": "sto",
            "list": "Y",
            "imageFile": "feature_point_stomion-frontal.png",
            "description": "Point at which the upper and lower lip make contact. Located along the labial fissure in the midline.",
            "references": "(18, 34)",
            "usedInMeasurements": [
                "Height_of_the_Mandible/Chin_Height",
                "Height_of_the_Mandible/Chin_Height_Surface",
                "Lower_Lip_Height",
                "Lower_Lip_Height_Surface",
                "Upper_Lip_Height",
                "Upper_Lip_Height_Surface"
            ],
            "xVal": -1.71,
            "yVal": -57.74,
            "zVal": 94.41,
            "cameraX": "",
            "cameraY": "",
            "cameraZ": "",
            "type": "Points"
        },
        {
            "id": "Subalare_left",
            "name": "Subalare - left",
            "abbrv": "sbal_l",
            "list": "Y",
            "imageFile": "feature_point_subalare_left-basal.png",
            "description": "The point at the lower limit of each alar base, where the alar base disappears into skin of the upper lip. A bilateral landmark located below the nostril opening at the point where the infero-medial continuation of the alar cartilage inserts into the skin of the upper lip.",
            "references": "(35, 36)",
            "usedInMeasurements": [
                "Nostril_Floor_Width_(left)",
                "Nostril_Floor_Width_(left)_Surface",
                "Subnasal_Width",
                "Subnasal_Width_Surface"
            ],
            "xVal": 12.06,
            "yVal": -31.7,
            "zVal": 96,
            "cameraX": "",
            "cameraY": "",
            "cameraZ": "",
            "type": "Points"
        },
        {
            "id": "Subalare_right",
            "name": "Subalare - right",
            "abbrv": "sbal_r",
            "list": "Y",
            "imageFile": "feature_point_subalare_right-basal.png",
            "description": "The point at the lower limit of each alar base, where the alar base disappears into skin of the upper lip. A bilateral landmark located below the nostril opening at the point where the infero-medial continuation of the alar cartilage inserts into the skin of the upper lip.",
            "references": "(35, 36)",
            "usedInMeasurements": [
                "Nostril_Floor_Width_(right)",
                "Nostril_Floor_Width_(right)_Surface",
                "Subnasal_Width",
                "Subnasal_Width_Surface"
            ],
            "xVal": -9.35,
            "yVal": -30.57,
            "zVal": 96.96,
            "cameraX": "",
            "cameraY": "",
            "cameraZ": "",
            "type": "Points"
        },
        {
            "id": "Subnasale_left",
            "name": "Subnasale - left",
            "abbrv": "sn_l",
            "list": "Y",
            "imageFile": "feature_point_subnasale_left-basal.png",
            "description": "Indicates the midpoint of the left columella crest where the thickness of the columella (sn'-sn') is measured.",
            "references": "(12)",
            "usedInMeasurements": [
                "Columella_Width_I_Surface",
                "Columella_Width_I",
                "Angle_of_Subnasale_left"
            ],
            "xVal": 7.27,
            "yVal": -30.82,
            "zVal": 97.06,
            "cameraX": "",
            "cameraY": "",
            "cameraZ": "",
            "type": "Points"
        },
        {
            "id": "Subnasale_right",
            "name": "Subnasale - right",
            "abbrv": "sn_r",
            "list": "Y",
            "imageFile": "feature_point_subnasale_right-basal.png",
            "description": "Indicates the midpoint of the right columella crest where the thickness of the columella (sn'-sn') is measured.",
            "references": "(12)",
            "usedInMeasurements": [
                "Columella_Width_I_Surface",
                "Columella_Width_I",
                "Angle_of_Subnasale_right"
            ],
            "xVal": -5.06,
            "yVal": -30.17,
            "zVal": 98.11,
            "cameraX": "",
            "cameraY": "",
            "cameraZ": "",
            "type": "Points"
        },
        {
            "id": "Subnasale",
            "name": "Subnasale",
            "abbrv": "sn",
            "list": "Y",
            "imageFile": "feature_point_subnasale-basal.png",
            "description": "The midpoint of the columella base. The deepest point at the junction of the base of the columella and the upper lip in the midline. Located at the apex of the nasolabial angle in the midline, where the inferior border of the nasal septum meets the skin of the upper lip.",
            "references": "(20)",
            "usedInMeasurements": [
                "Columella_Length_Surface",
                "Columella_Length",
                "Lower_Facial_Height",
                "Lower_Facial_Height_Surface",
                "Mid-Facial_Height",
                "Mid-Facial_Height_Surface",
                "Nasal_Tip_Projection",
                "Nasal_Tip_Projection_Surface",
                "Nose_Height",
                "Nose_Height_Surface",
                "Nostril_Floor_Width_(left)",
                "Nostril_Floor_Width_(left)_Surface",
                "Nostril_Floor_Width_(right)",
                "Nostril_Floor_Width_(right)_Surface",
                "Premaxilla_-_left",
                "Premaxilla_-_left_Surface",
                "Premaxilla_-_right",
                "Premaxilla_-_right_Surface",
                "Upper_Lip_Height",
                "Upper_Lip_Height_Surface",
                "Columellar_Labial_Angle",
                "Columellar_Lobular_Angle",
                "Nasal_Tip_Angle",
                "Nasolabial_Angle_I",
                "Nasal_Tip_Projection:_Baum",
                "Nasal_Tip_Projection:_Powell_and_Humphries",
                "Nasal_Tip_Projection:_Simons"
            ],
            "xVal": 0.91,
            "yVal": -35.49,
            "zVal": 96.26,
            "cameraX": "",
            "cameraY": "",
            "cameraZ": "",
            "type": "Points"
        },
        {
            "id": "Supratip_Break_Point",
            "name": "Supratip Break Point",
            "abbrv": "s",
            "list": "Y",
            "imageFile": "feature_point_supratip_break_point-lateral(l).png",
            "description": "The area just cephalad to the nasal tip at the caudal portion of the nasal dorsum.",
            "references": "(38)",
            "usedInMeasurements": [
                "Supratip_Lobule",
                "Supratip_Lobule_Surface"
            ],
            "xVal": 2.18,
            "yVal": -7.04,
            "zVal": 97.81,
            "cameraX": "",
            "cameraY": "",
            "cameraZ": "",
            "type": "Points"
        },
        {
            "id": "Tip_Defining_Point_left",
            "name": "Tip Defining Point - left",
            "abbrv": "td_l",
            "list": "Y",
            "imageFile": "feature_point_tip_defining_point_left-frontal.png",
            "description": "The nasal tip defining point (TDP) is the most anterior projection of the tip cartilages, usually corresponding to the apex of the lobular arch anatomically, and is typically identified externally where the light reflex is seen on the nasal tip.",
            "references": "(39)",
            "usedInMeasurements": [
                "Tip/Lobule_Width",
                "Tip/Lobule_Width_Surface",
                "Lobule_-_Base_Ratio"
            ],
            "xVal": 10.78,
            "yVal": -20.22,
            "zVal": 102.02,
            "cameraX": "",
            "cameraY": "",
            "cameraZ": "",
            "type": "Points"
        },
        {
            "id": "Tip_Defining_Point_right",
            "name": "Tip Defining Point - right",
            "abbrv": "td_r",
            "list": "Y",
            "imageFile": "feature_point_tip_defining_point_right-frontal.png",
            "description": "The nasal tip defining point (TDP) is the most anterior projection of the tip cartilages, usually corresponding to the apex of the lobular arch anatomically, and is typically identified externally where the light reflex is seen on the nasal tip.",
            "references": "(39)",
            "usedInMeasurements": [
                "Tip/Lobule_Width",
                "Tip/Lobule_Width_Surface",
                "Lobule_-_Base_Ratio"
            ],
            "xVal": -5.88,
            "yVal": -19.44,
            "zVal": 105.29,
            "cameraX": "",
            "cameraY": "",
            "cameraZ": "",
            "type": "Points"
        },
        {
            "id": "Trichion",
            "name": "Trichion",
            "abbrv": "tr",
            "list": "Y",
            "imageFile": "feature_point_trichion-frontal.png",
            "description": "The point on the hairline in the midline of the forehead.",
            "references": "(19)",
            "usedInMeasurements": [
                "Face_Length/Height",
                "Face_Length/Height_Surface",
                "Upper_Facial_Height"
            ],
            "xVal": 2.88,
            "yVal": 108.02,
            "zVal": 40.22,
            "cameraX": "",
            "cameraY": "",
            "cameraZ": "",
            "type": "Points"
        },
        {
            "id": "Zygion_left",
            "name": "Zygion - left",
            "abbrv": "zy_l",
            "list": "Y",
            "imageFile": "feature_point_zygion_left-frontal.png",
            "description": "The most lateral point of left zygomatic arch.",
            "references": "(14)",
            "usedInMeasurements": [
                "Face_Width",
                "Face_Width_Surface"
            ],
            "xVal": 56.89,
            "yVal": -16.94,
            "zVal": 79.35,
            "cameraX": "",
            "cameraY": "",
            "cameraZ": "",
            "type": "Points"
        },
        {
            "id": "Zygion_right",
            "name": "Zygion - right",
            "abbrv": "zy_r",
            "list": "Y",
            "imageFile": "feature_point_zygion_right-frontal.png",
            "description": "The most lateral point of right zygomatic arch.",
            "references": "(14)",
            "usedInMeasurements": [
                "Face_Width",
                "Face_Width_Surface"
            ],
            "xVal": -62.54,
            "yVal": -21.29,
            "zVal": 76.49,
            "cameraX": "",
            "cameraY": "",
            "cameraZ": "",
            "type": "Points"
        }
    ],
    "measurements": [
        {
            "id": "Alar_Base_Width",
            "name": "Alar Base Width",
            "surfaceDistId": "Alar_Base_Width_Surface",
            "imageFile": "measurement_distance_alar_base_width-basal.png",
            "description": "The distance from alar base junction/alar crease - left (ac_l) to alar base junction/alar crease - right (ac_r)",
            "type": "Distances",
            "group": "Distances",
            "list": "Y",
            "references": "(25, 51)",
            "usedFeatures": [
                "Alar_Crest/Alar_Curvature/Alar_Base_Junction/Alar-Facial_Groove/Alar-Cheek_Junction/Alar_Crease_left",
                "Alar_Crest/Alar_Curvature/Alar_Base_Junction/Alar-Facial_Groove/Alar-Cheek_Junction/Alar_Crease_right"
            ],
            "beginningPoint": {
                "x": 0,
                "y": 0,
                "z": 0
            },
            "endPoint": {
                "x": 0,
                "y": 0,
                "z": 0
            },
            "value": "31.07",
            "cameraX": "",
            "cameraY": "",
            "cameraZ": "",
            "formula": "$$\\sqrt{\\left(Ac_l.x-Ac_r.x\\right)^2+\\left(Ac_l.y-Ac_r.y\\right)^2+\\left(Ac_l.z-Ac_r.z\\right)^2}$$",
            "rangeStart": "1",
            "rangeEnd": "200"
        },
        {
            "id": "Columella_Length_I",
            "name": "Columella Length",
            "surfaceDistId": "Columella_Length_I_Surface",
            "imageFile": "measurement_distance_columella_length_I-lateral(l).png",
            "description": "The distance between subnasale (sn) and columella breakpoint (cb)",
            "type": "Distances",
            "group": "Distances",
            "list": "Y",
            "references": "(54)",
            "usedFeatures": [
                "Subnasale",
                "Columellar_Break_Point"
            ],
            "beginningPoint": {
                "x": 0,
                "y": 0,
                "z": 0
            },
            "endPoint": {
                "x": 0,
                "y": 0,
                "z": 0
            },
            "value": "9.00",
            "cameraX": "",
            "cameraY": "",
            "cameraZ": "",
            "formula": "$$\\sqrt{\\left(Sn.x-C.x\\right)^2+\\left(Sn.y-C.y\\right)^2+\\left(Sn.z-C.z\\right)^2}$$",
            "rangeStart": "1",
            "rangeEnd": "200"
        },
        {
            "id": "Columella_Width_I",
            "name": "Columella Width",
            "surfaceDistId": "Columella_Width_I_Surface",
            "imageFile": "measurement_distance_columella_width_I-basal.png",
            "description": "The distance from subnasale - left (sn_l) to subnasale - right (sn_r)",
            "type": "Distances",
            "group": "Distances",
            "list": "Y",
            "references": "(12, 51, 52, 54)",
            "usedFeatures": [
                "Subnasale_left",
                "Subnasale_right"
            ],
            "beginningPoint": {
                "x": 0,
                "y": 0,
                "z": 0
            },
            "endPoint": {
                "x": 0,
                "y": 0,
                "z": 0
            },
            "value": "12.39",
            "cameraX": "",
            "cameraY": "",
            "cameraZ": "",
            "formula": "$$\\sqrt{\\left(Sn’_l.x-Sn’_r.x\\right)^2+\\left(Sn’_l.y-Sn’_r.y\\right)^2+\\left(Sn’_l.z-Sn’_r.z\\right)^2}$$",
            "rangeStart": "1",
            "rangeEnd": "200"
        },
        {
            "id": "Distance_between_sill_base_junction_and_alar_flare",
            "name": "Distance between sill-base junction and alar flare",
            "surfaceDistId": "Distance_between_sill_base_junction_and_alar_flare_Surface",
            "imageFile": "measurement_distance_distance_between_sill_base_junction_and_alar_flare.png",
            "description": "The relative vertical relationship between these 2 points on basal view analysis.",
            "type": "Distances",
            "group": "Distances",
            "list": "Y",
            "references": "(10)",
            "usedFeatures": [
                "Sill-Base Junction_left",
                "Alare/Alar_Flare_left"
            ],
            "beginningPoint": {
                "x": 0,
                "y": 0,
                "z": 0
            },
            "endPoint": {
                "x": 0,
                "y": 0,
                "z": 0
            },
            "value": "6.87",
            "cameraX": "",
            "cameraY": "",
            "cameraZ": "",
            "formula": "",
            "rangeStart": "1",
            "rangeEnd": "200"
        },
        {
            "id": "Interalar_Distance",
            "name": "Interalar Distance",
            "surfaceDistId": "Interalar_Distance_Surface",
            "imageFile": "measurement_distance_interalar_distance-frontal.png",
            "description": "The distance from alare/alar flare - left (al_l) to alar/alar flare - right (al_r).",
            "type": "Distances",
            "group": "Distances",
            "list": "Y",
            "references": "(12, 18, 25, 48, 51, 59, 60",
            "usedFeatures": [
                "Alare/Alar_Flare_left",
                "Alare/Alar_Flare_right"
            ],
            "beginningPoint": {
                "x": 0,
                "y": 0,
                "z": 0
            },
            "endPoint": {
                "x": 0,
                "y": 0,
                "z": 0
            },
            "value": "27.09",
            "cameraX": "",
            "cameraY": "",
            "cameraZ": "",
            "formula": "$$\\sqrt{\\left(Al_l.x-Al_r.x\\right)^2+\\left(Al_l.y-Al_r.y\\right)^2+\\left(Al_l.z-Al_r.z\\right)^2}$$",
            "rangeStart": "1",
            "rangeEnd": "200"
        },
        {
            "id": "Nasal_Bridge_Length",
            "name": "Nasal Bridge Length",
            "surfaceDistId": "Nasal_Bridge_Length_Surface",
            "imageFile": "measurement_distance_nasal_bridge_length-lateral(l).png",
            "description": "The distance from pronasale/tip (prn) to nasion (n)",
            "type": "Distances",
            "group": "Distances",
            "list": "Y",
            "references": "(17, 18, 51, 52)",
            "usedFeatures": [
                "Pronasale/Tip",
                "Nasion/Radix"
            ],
            "beginningPoint": {
                "x": 0,
                "y": 0,
                "z": 0
            },
            "endPoint": {
                "x": 0,
                "y": 0,
                "z": 0
            },
            "value": "50.22",
            "cameraX": "",
            "cameraY": "",
            "cameraZ": "",
            "formula": "$$\\sqrt{\\left(Prn.x-N.x\\right)^2+\\left(Prn.y-N.y\\right)^2+\\left(Prn.z-N.z\\right)^2}$$",
            "rangeStart": "1",
            "rangeEnd": "200"
        },
        {
            "id": "Nasal_Tip_Projection",
            "name": "Nasal Tip Projection",
            "surfaceDistId": "Nasal_Tip_Projection_Surface",
            "imageFile": "measurement_distance_nasal_tip_projection_I-lateral(l).png",
            "description": "The distance from pronasale/Tip (prn) to subnasale (sn)",
            "type": "Distances",
            "group": "Distances",
            "list": "Y",
            "references": "(64)",
            "usedFeatures": [
                "Subnasale",
                "Pronasale/Tip"
            ],
            "beginningPoint": {
                "x": 0,
                "y": 0,
                "z": 0
            },
            "endPoint": {
                "x": 0,
                "y": 0,
                "z": 0
            },
            "value": "22.78",
            "cameraX": "",
            "cameraY": "",
            "cameraZ": "",
            "formula": "$$\\sqrt{\\left(Prn.x-Sn.x\\right)^2+\\left(Prn.y-Sn.y\\right)^2+\\left(Prn.z-Sn.z\\right)^2}$$",
            "rangeStart": "1",
            "rangeEnd": "200"
        },
        {
            "id": "Alar_Base_Width_Surface",
            "name": "Alar Base Width - Surface",
            "flyDistId": "Alar_Base_Width",
            "numberOfSegments": 32,
            "imageFile": "measurement_distance_alar_base_width-basal.png",
            "description": "The surface distance from alar base junction/alar crease - left (ac_l) to alar base junction/alar crease - right (ac_r)",
            "type": "Distances - Surface",
            "group": "Surface Distances",
            "typeOfView": "basal",
            "references": "Please check the corresponding 'not surface' measurement",
            "referencesFly": "(25, 51)",
            "storedPoints": [
                {
                    "x": 14.38,
                    "y": -31.57,
                    "z": 95.59
                },
                {
                    "x": 13.4,
                    "y": -31.78,
                    "z": 96
                },
                {
                    "x": 12.43,
                    "y": -31.79,
                    "z": 95.92
                },
                {
                    "x": 11.46,
                    "y": -31.87,
                    "z": 96.01
                },
                {
                    "x": 10.49,
                    "y": -31.94,
                    "z": 96.07
                },
                {
                    "x": 9.52,
                    "y": -31.99,
                    "z": 96.09
                },
                {
                    "x": 8.55,
                    "y": -32.04,
                    "z": 96.12
                },
                {
                    "x": 7.58,
                    "y": -32.04,
                    "z": 96
                },
                {
                    "x": 6.62,
                    "y": -32.08,
                    "z": 96
                },
                {
                    "x": 5.65,
                    "y": -32.21,
                    "z": 96.21
                },
                {
                    "x": 4.67,
                    "y": -32.36,
                    "z": 96.48
                },
                {
                    "x": 3.7,
                    "y": -32.58,
                    "z": 96.91
                },
                {
                    "x": 2.74,
                    "y": -32.78,
                    "z": 97.29
                },
                {
                    "x": 1.77,
                    "y": -32.95,
                    "z": 97.59
                },
                {
                    "x": 0.8,
                    "y": -33.07,
                    "z": 97.79
                },
                {
                    "x": -0.16,
                    "y": -33.05,
                    "z": 97.64
                },
                {
                    "x": -1.12,
                    "y": -32.97,
                    "z": 97.34
                },
                {
                    "x": -2.09,
                    "y": -32.87,
                    "z": 96.98
                },
                {
                    "x": -3.06,
                    "y": -32.77,
                    "z": 96.64
                },
                {
                    "x": -4.03,
                    "y": -32.65,
                    "z": 96.26
                },
                {
                    "x": -5.97,
                    "y": -32.55,
                    "z": 95.8
                },
                {
                    "x": -6.93,
                    "y": -32.56,
                    "z": 95.72
                },
                {
                    "x": -7.9,
                    "y": -32.59,
                    "z": 95.7
                },
                {
                    "x": -8.87,
                    "y": -32.65,
                    "z": 95.73
                },
                {
                    "x": -9.83,
                    "y": -32.68,
                    "z": 95.72
                },
                {
                    "x": -10.8,
                    "y": -32.72,
                    "z": 95.71
                },
                {
                    "x": -11.77,
                    "y": -32.77,
                    "z": 95.71
                },
                {
                    "x": -12.74,
                    "y": -32.75,
                    "z": 95.57
                },
                {
                    "x": -13.71,
                    "y": -32.68,
                    "z": 95.29
                },
                {
                    "x": -14.68,
                    "y": -32.77,
                    "z": 95.41
                }
            ],
            "list": "Y",
            "usedFeatures": [
                "Alar_Crest/Alar_Curvature/Alar_Base_Junction/Alar-Facial_Groove/Alar-Cheek_Junction/Alar_Crease_left",
                "Alar_Crest/Alar_Curvature/Alar_Base_Junction/Alar-Facial_Groove/Alar-Cheek_Junction/Alar_Crease_right"
            ],
            "value": "32.58",
            "cameraX": "",
            "cameraY": "",
            "cameraZ": "",
            "formula": "",
            "rangeStart": "1",
            "rangeEnd": "200"
        },
        {
            "id": "Columella_Length_I_Surface",
            "name": "Columella Length - Surface",
            "flyDistId": "Columella_Length_I",
            "numberOfSegments": 10,
            "imageFile": "measurement_distance_columella_length_I-lateral(l).png",
            "description": "The surface distance between subnasale (sn) and columella breakpoint (cb)",
            "type": "Distances - Surface",
            "group": "Surface Distances",
            "typeOfView": "front",
            "references": "Please check the corresponding 'not surface' measurement",
            "referencesFly": "(54)",
            "storedPoints": [
                {
                    "x": 0.767,
                    "y": -34.787,
                    "z": 96.59
                },
                {
                    "x": 0.624,
                    "y": -34.084,
                    "z": 97.03
                },
                {
                    "x": 0.481,
                    "y": -33.381,
                    "z": 97.57
                },
                {
                    "x": 0.33799999999999997,
                    "y": -32.678000000000004,
                    "z": 98.1
                },
                {
                    "x": 0.19499999999999995,
                    "y": -31.975,
                    "z": 98.63
                },
                {
                    "x": 0.051999999999999935,
                    "y": -31.272000000000002,
                    "z": 99.34
                },
                {
                    "x": -0.09100000000000008,
                    "y": -30.569000000000003,
                    "z": 99.89
                },
                {
                    "x": -0.2340000000000001,
                    "y": -29.866,
                    "z": 100.44
                },
                {
                    "x": -0.3770000000000001,
                    "y": -29.163,
                    "z": 101.06
                }
            ],
            "list": "Y",
            "usedFeatures": [
                "Subnasale",
                "Columellar_Break_Point"
            ],
            "value": "9.04",
            "cameraX": "",
            "cameraY": "",
            "cameraZ": "",
            "formula": "",
            "rangeStart": "1",
            "rangeEnd": "200"
        },
        {
            "id": "Columella_Width_I_Surface",
            "name": "Columella Width - Surface",
            "flyDistId": "Columella_Width_I",
            "numberOfSegments": 13,
            "imageFile": "measurement_distance_columella_width_I-basal.png",
            "description": "The surface distance from subnasale - left (sn_l) to subnasale - right (sn_r)",
            "type": "Distances - Surface",
            "group": "Surface Distances",
            "typeOfView": "steepBasal",
            "references": "Please check the corresponding 'not surface' measurement",
            "referencesFly": "(12, 51, 52, 54)",
            "storedPoints": [
                {
                    "x": 6.32,
                    "y": -31.06,
                    "z": 97.3
                },
                {
                    "x": 5.37,
                    "y": -31.16,
                    "z": 97.46
                },
                {
                    "x": 4.42,
                    "y": -31.25,
                    "z": 97.61
                },
                {
                    "x": 3.47,
                    "y": -31.61,
                    "z": 97.92
                },
                {
                    "x": 2.52,
                    "y": -31.92,
                    "z": 98.19
                },
                {
                    "x": 1.58,
                    "y": -32.09,
                    "z": 98.39
                },
                {
                    "x": 0.63,
                    "y": -32.16,
                    "z": 98.54
                },
                {
                    "x": -0.32,
                    "y": -31.96,
                    "z": 98.53
                },
                {
                    "x": -1.26,
                    "y": -31.7,
                    "z": 98.5
                },
                {
                    "x": -2.21,
                    "y": -31.25,
                    "z": 98.37
                },
                {
                    "x": -3.16,
                    "y": -30.79,
                    "z": 98.23
                },
                {
                    "x": -4.11,
                    "y": -31.31,
                    "z": 98.61
                }
            ],
            "list": "Y",
            "usedFeatures": [
                "Subnasale_left",
                "Subnasale_right"
            ],
            "value": "13.77",
            "cameraX": "",
            "cameraY": "",
            "cameraZ": "",
            "formula": "",
            "rangeStart": "1",
            "rangeEnd": "200"
        },
        {
            "id": "Interalar_Distance_Surface",
            "name": "Interalar Distance - Surface",
            "flyDistId": "Interalar_Distance",
            "numberOfSegments": 28,
            "imageFile": "measurement_distance_interalar_distance-frontal.png",
            "description": "The surface distance from alare/alar flare - left (al_l) to alar/alar flare - right (al_r).",
            "type": "Distances - Surface",
            "group": "Surface Distances",
            "typeOfView": "front",
            "references": "Please check the corresponding 'not surface' measurement",
            "referencesFly": "(12, 18, 25, 48, 51, 59, 60",
            "storedPoints": [
                {
                    "x": 13.332500000000001,
                    "y": -26.111428571428572,
                    "z": 98.45
                },
                {
                    "x": 12.365,
                    "y": -26.11285714285714,
                    "z": 99.01
                },
                {
                    "x": 11.3975,
                    "y": -26.114285714285714,
                    "z": 99.5
                },
                {
                    "x": 10.43,
                    "y": -26.115714285714287,
                    "z": 99.99
                },
                {
                    "x": 9.4625,
                    "y": -26.117142857142856,
                    "z": 100.49
                },
                {
                    "x": 8.495000000000001,
                    "y": -26.11857142857143,
                    "z": 100.99
                },
                {
                    "x": 7.527500000000001,
                    "y": -26.119999999999997,
                    "z": 101.48
                },
                {
                    "x": 6.5600000000000005,
                    "y": -26.12142857142857,
                    "z": 101.98
                },
                {
                    "x": 5.592500000000001,
                    "y": -26.122857142857143,
                    "z": 102.5
                },
                {
                    "x": 4.625,
                    "y": -26.124285714285712,
                    "z": 103
                },
                {
                    "x": 3.6575000000000006,
                    "y": -26.125714285714285,
                    "z": 103.48
                },
                {
                    "x": 2.6900000000000013,
                    "y": -26.127142857142857,
                    "z": 103.92
                },
                {
                    "x": 1.7225000000000001,
                    "y": -26.128571428571426,
                    "z": 104.15
                },
                {
                    "x": 0.7550000000000008,
                    "y": -26.13,
                    "z": 104.34
                },
                {
                    "x": -0.21250000000000036,
                    "y": -26.13142857142857,
                    "z": 104.11
                },
                {
                    "x": -1.1799999999999997,
                    "y": -26.13285714285714,
                    "z": 103.9
                },
                {
                    "x": -2.147500000000001,
                    "y": -26.134285714285713,
                    "z": 103.45
                },
                {
                    "x": -3.1149999999999984,
                    "y": -26.135714285714286,
                    "z": 103.09
                },
                {
                    "x": -4.0825,
                    "y": -26.137142857142855,
                    "z": 102.62
                },
                {
                    "x": -5.050000000000001,
                    "y": -26.138571428571428,
                    "z": 102.03
                },
                {
                    "x": -6.017499999999998,
                    "y": -26.14,
                    "z": 101.46
                },
                {
                    "x": -6.984999999999999,
                    "y": -26.14142857142857,
                    "z": 100.95
                },
                {
                    "x": -7.952500000000001,
                    "y": -26.142857142857142,
                    "z": 100.45
                },
                {
                    "x": -8.919999999999998,
                    "y": -26.14428571428571,
                    "z": 100.03
                },
                {
                    "x": -9.8875,
                    "y": -26.145714285714284,
                    "z": 99.75
                },
                {
                    "x": -10.855,
                    "y": -26.147142857142857,
                    "z": 99.29
                },
                {
                    "x": -11.822500000000002,
                    "y": -26.148571428571426,
                    "z": 98.73
                }
            ],
            "list": "Y",
            "usedFeatures": [
                "Alare/Alar_Flare_left",
                "Alare/Alar_Flare_right"
            ],
            "value": "30.19",
            "cameraX": "",
            "cameraY": "",
            "cameraZ": "",
            "formula": "",
            "rangeStart": "1",
            "rangeEnd": "200"
        },
        {
            "id": "Nasal_Bridge_Length_Surface",
            "name": "Nasal Bridge Length - Surface",
            "flyDistId": "Nasal_Bridge_Length",
            "numberOfSegments": 51,
            "imageFile": "measurement_distance_nasal_bridge_length-lateral(l).png",
            "description": "The surface distance from pronasale/tip (prn) to nasion (n)",
            "type": "Distances - Surface",
            "group": "Surface Distances",
            "typeOfView": "front",
            "references": "Please check the corresponding 'not surface' measurement",
            "referencesFly": "(17, 18, 51, 52)",
            "storedPoints": [
                {
                    "x": 0.4801960784313726,
                    "y": -15.025686274509804,
                    "z": 107.19
                },
                {
                    "x": 0.5003921568627451,
                    "y": -14.201372549019608,
                    "z": 106.24
                },
                {
                    "x": 0.5205882352941177,
                    "y": -13.377058823529412,
                    "z": 104.92
                },
                {
                    "x": 0.5407843137254902,
                    "y": -12.552745098039216,
                    "z": 103.8
                },
                {
                    "x": 0.5609803921568628,
                    "y": -11.728431372549018,
                    "z": 102.76
                },
                {
                    "x": 0.5811764705882353,
                    "y": -10.904117647058822,
                    "z": 101.84
                },
                {
                    "x": 0.6013725490196078,
                    "y": -10.079803921568626,
                    "z": 100.97
                },
                {
                    "x": 0.6215686274509804,
                    "y": -9.25549019607843,
                    "z": 100.12
                },
                {
                    "x": 0.641764705882353,
                    "y": -8.431176470588234,
                    "z": 99.36
                },
                {
                    "x": 0.6619607843137255,
                    "y": -7.606862745098038,
                    "z": 98.6
                },
                {
                    "x": 0.682156862745098,
                    "y": -6.782549019607842,
                    "z": 97.84
                },
                {
                    "x": 0.7023529411764706,
                    "y": -5.958235294117646,
                    "z": 97.09
                },
                {
                    "x": 0.7225490196078431,
                    "y": -5.13392156862745,
                    "z": 96.36
                },
                {
                    "x": 0.7427450980392156,
                    "y": -4.309607843137254,
                    "z": 95.63
                },
                {
                    "x": 0.7629411764705882,
                    "y": -3.485294117647058,
                    "z": 94.89
                },
                {
                    "x": 0.7831372549019608,
                    "y": -2.660980392156862,
                    "z": 94.15
                },
                {
                    "x": 0.8033333333333333,
                    "y": -1.836666666666666,
                    "z": 93.41
                },
                {
                    "x": 0.8235294117647058,
                    "y": -1.01235294117647,
                    "z": 92.67
                },
                {
                    "x": 0.8437254901960785,
                    "y": -0.18803921568627402,
                    "z": 91.94
                },
                {
                    "x": 0.8639215686274511,
                    "y": 0.6362745098039237,
                    "z": 91.26
                },
                {
                    "x": 0.8841176470588235,
                    "y": 1.4605882352941197,
                    "z": 90.57
                },
                {
                    "x": 0.9043137254901961,
                    "y": 2.2849019607843157,
                    "z": 89.88
                },
                {
                    "x": 0.9245098039215687,
                    "y": 3.1092156862745117,
                    "z": 89.19
                },
                {
                    "x": 0.9447058823529412,
                    "y": 3.9335294117647077,
                    "z": 88.5
                },
                {
                    "x": 0.9649019607843137,
                    "y": 4.757843137254904,
                    "z": 87.82
                },
                {
                    "x": 0.9850980392156863,
                    "y": 5.5821568627451,
                    "z": 87.17
                },
                {
                    "x": 1.005294117647059,
                    "y": 6.406470588235296,
                    "z": 86.52
                },
                {
                    "x": 1.0254901960784313,
                    "y": 7.230784313725492,
                    "z": 85.87
                },
                {
                    "x": 1.045686274509804,
                    "y": 8.055098039215688,
                    "z": 85.24
                },
                {
                    "x": 1.0658823529411765,
                    "y": 8.879411764705884,
                    "z": 84.7
                },
                {
                    "x": 1.0860784313725491,
                    "y": 9.70372549019608,
                    "z": 84.21
                },
                {
                    "x": 1.1062745098039215,
                    "y": 10.528039215686276,
                    "z": 83.73
                },
                {
                    "x": 1.1264705882352941,
                    "y": 11.352352941176472,
                    "z": 83.28
                },
                {
                    "x": 1.1466666666666667,
                    "y": 12.176666666666668,
                    "z": 82.85
                },
                {
                    "x": 1.1668627450980391,
                    "y": 13.000980392156864,
                    "z": 82.49
                },
                {
                    "x": 1.1870588235294117,
                    "y": 13.82529411764706,
                    "z": 82.19
                },
                {
                    "x": 1.2072549019607843,
                    "y": 14.649607843137256,
                    "z": 81.91
                },
                {
                    "x": 1.227450980392157,
                    "y": 15.473921568627452,
                    "z": 81.71
                },
                {
                    "x": 1.2476470588235293,
                    "y": 16.298235294117646,
                    "z": 81.53
                },
                {
                    "x": 1.267843137254902,
                    "y": 17.122549019607845,
                    "z": 81.33
                },
                {
                    "x": 1.2880392156862746,
                    "y": 17.946862745098038,
                    "z": 81.19
                },
                {
                    "x": 1.308235294117647,
                    "y": 18.771176470588237,
                    "z": 81.08
                },
                {
                    "x": 1.3284313725490196,
                    "y": 19.59549019607843,
                    "z": 80.96
                },
                {
                    "x": 1.3486274509803922,
                    "y": 20.41980392156863,
                    "z": 80.83
                },
                {
                    "x": 1.3688235294117648,
                    "y": 21.24411764705882,
                    "z": 80.72
                },
                {
                    "x": 1.3890196078431372,
                    "y": 22.06843137254902,
                    "z": 80.63
                },
                {
                    "x": 1.4092156862745098,
                    "y": 22.892745098039214,
                    "z": 80.55
                },
                {
                    "x": 1.4294117647058824,
                    "y": 23.717058823529413,
                    "z": 80.47
                },
                {
                    "x": 1.4496078431372548,
                    "y": 24.541372549019606,
                    "z": 80.39
                },
                {
                    "x": 1.4698039215686274,
                    "y": 25.365686274509805,
                    "z": 80.36
                }
            ],
            "list": "Y",
            "usedFeatures": [
                "Pronasale/Tip",
                "Nasion/Radix"
            ],
            "value": "52.11",
            "cameraX": "",
            "cameraY": "",
            "cameraZ": "",
            "formula": "",
            "rangeStart": "1",
            "rangeEnd": "200"
        },
        {
            "id": "Nasal_Tip_Projection_Surface",
            "name": "Nasal Tip Projection - Surface",
            "numberOfSegments": 23,
            "imageFile": "measurement_distance_nasal_tip_projection_I-lateral(l).png",
            "description": "The surface distance from pronasale/Tip (prn) to subnasale (sn)",
            "type": "Distances - Surface",
            "group": "Surface Distances",
            "typeOfView": "front",
            "references": "Please check the corresponding 'not surface' measurement",
            "referencesFly": "(64)",
            "storedPoints": [
                {
                    "x": 0.8904347826086957,
                    "y": -34.636086956521744,
                    "z": 96.64
                },
                {
                    "x": 0.8708695652173913,
                    "y": -33.78217391304348,
                    "z": 97.23
                },
                {
                    "x": 0.851304347826087,
                    "y": -32.92826086956522,
                    "z": 97.89
                },
                {
                    "x": 0.8317391304347826,
                    "y": -32.07434782608696,
                    "z": 98.56
                },
                {
                    "x": 0.8121739130434783,
                    "y": -31.2204347826087,
                    "z": 99.47
                },
                {
                    "x": 0.792608695652174,
                    "y": -30.366521739130437,
                    "z": 100.36
                },
                {
                    "x": 0.7730434782608696,
                    "y": -29.512608695652176,
                    "z": 101.22
                },
                {
                    "x": 0.7534782608695653,
                    "y": -28.658695652173915,
                    "z": 102.05
                },
                {
                    "x": 0.7339130434782609,
                    "y": -27.804782608695653,
                    "z": 102.82
                },
                {
                    "x": 0.7143478260869566,
                    "y": -26.950869565217392,
                    "z": 103.6
                },
                {
                    "x": 0.6947826086956522,
                    "y": -26.09695652173913,
                    "z": 104.35
                },
                {
                    "x": 0.6752173913043478,
                    "y": -25.243043478260873,
                    "z": 105.11
                },
                {
                    "x": 0.6556521739130434,
                    "y": -24.389130434782608,
                    "z": 105.77
                },
                {
                    "x": 0.6360869565217391,
                    "y": -23.53521739130435,
                    "z": 106.41
                },
                {
                    "x": 0.6165217391304347,
                    "y": -22.68130434782609,
                    "z": 107.07
                },
                {
                    "x": 0.5969565217391304,
                    "y": -21.827391304347827,
                    "z": 107.5
                },
                {
                    "x": 0.577391304347826,
                    "y": -20.973478260869566,
                    "z": 107.89
                },
                {
                    "x": 0.5578260869565217,
                    "y": -20.119565217391305,
                    "z": 108.24
                },
                {
                    "x": 0.5382608695652173,
                    "y": -19.265652173913043,
                    "z": 108.37
                },
                {
                    "x": 0.518695652173913,
                    "y": -18.411739130434782,
                    "z": 108.49
                },
                {
                    "x": 0.4991304347826087,
                    "y": -17.557826086956524,
                    "z": 108.46
                },
                {
                    "x": 0.47956521739130437,
                    "y": -16.703913043478263,
                    "z": 108.25
                }
            ],
            "list": "Y",
            "usedFeatures": [
                "Subnasale",
                "Pronasale/Tip"
            ],
            "value": "24.08",
            "cameraX": "",
            "cameraY": "",
            "cameraZ": "",
            "formula": "",
            "rangeStart": "1",
            "rangeEnd": "200"
        },
        {
            "id": "Interalar_Angle",
            "name": "Interalar Angle",
            "imageFile": "measurement_angle_interalar_angle-basal.png",
            "description": "The angle from alare/alar flare – right (al_r) to nasal tip/pronasale (prn) to alare/alar flare – left (al_l).",
            "type": "Angles",
            "group": "Angles",
            "list": "Y",
            "references": "(52, 79)",
            "usedFeatures": [
                "Pronasale/Tip",
                "Alare/Alar_Flare_left",
                "Alare/Alar_Flare_right"
            ],
            "linePointsOrder": [
                "Alare/Alar_Flare_right",
                "Pronasale/Tip",
                "Alare/Alar_Flare_left"
            ],
            "value": "93.04",
            "cameraX": "",
            "cameraY": "",
            "cameraZ": "",
            "formula": "V1=$$<\\left(Al_l.x-Prn.x\\right),\\left(Al_l.y-Prn.y\\right),\\left(Al_l.z-Prn.z\\right)>$$ V2=$$<\\left(Prn.x-Al_r.x\\right),\\left(Prn.y-Al_r.y\\right),\\left(Prn.z-Al_r.z\\right)>$$$$\\theta=\\cos^{-1}(\\frac{V1\\bullet V2}{|V1||V2|})$$"
        },
        {
            "id": "Nasal_Tip_Angle",
            "name": "Nasal Tip Angle",
            "imageFile": "measurement_angle_nasal_tip_angle-lateral(l).png",
            "description": "The angle between nasion/radix (n) to pronasale/tip (prn) to subnasale (sn).",
            "type": "Angles",
            "group": "Angles",
            "list": "Y",
            "references": "(12, 25, 52)",
            "usedFeatures": [
                "Pronasale/Tip",
                "Nasion/Radix",
                "Subnasale"
            ],
            "linePointsOrder": [
                "Subnasale",
                "Pronasale/Tip",
                "Nasion/Radix"
            ],
            "value": "63.63",
            "cameraX": "",
            "cameraY": "",
            "cameraZ": "",
            "formula": "V1=$$<\\left(N.x-Prn.x\\right),\\left(N.y-Prn.y\\right),\\left(N.z-Prn.z\\right)>$$ V2=$$<\\left(Prn.x-Sn.x\\right),\\left(Prn.y-Sn.y\\right),\\left(Prn.z-Sn.z\\right)>$$$$\\theta=\\cos^{-1}(\\frac{V1\\bullet V2}{|V1||V2|})$$"
        },
        {
            "id": "Nasofrontal_Angle",
            "name": "Nasofrontal Angle",
            "imageFile": "measurement_angle_nasofrontal_angle-lateral(l).png",
            "description": "The angle from glabella (g) to nasion/radix (n) to pronasale/tip (prn)",
            "type": "Angles",
            "group": "Angles",
            "list": "Y",
            "references": "(20, 59, 78)",
            "usedFeatures": [
                "Glabella",
                "Nasion/Radix",
                "Pronasale/Tip"
            ],
            "value": "145.53",
            "cameraX": "",
            "cameraY": "",
            "cameraZ": "",
            "formula": "V1=$$<\\left(N.x-G.x\\right),\\left(N.y-G.y\\right),\\left(N.z-G.z\\right)>$$ V2=$$<\\left(N.x-Prn.x\\right),\\left(N.y-Prn.y\\right),\\left(N.z-Prn.z\\right)>$$$$\\theta=\\cos^{-1}(\\frac{V1\\bullet V2}{|V1||V2|})$$"
        },
        {
            "id": "Nasal_Tip_Projection:_Goode",
            "name": "Nasal Tip Projection: Goode",
            "imageFile": "measurement_ratio_nasal_tip_projection_goode-lateral(l).png",
            "description": "The distance from pronasale (prn) to alar base junction/alar crease - right (ac_r) divided by the distance from nasion (n) to nasal tip/pronasale (prn).",
            "type": "Ratios",
            "group": "Ratios",
            "list": "Y",
            "references": "(85, 86, 89)",
            "usedFeatures": [
                "Pronasale/Tip",
                "Nasion/Radix",
                "Alar_Crest/Alar_Curvature/Alar_Base_Junction/Alar-Facial_Groove/Alar-Cheek_Junction/Alar_Crease_left"
            ],
            "value": "0.50",
            "cameraX": "",
            "cameraY": "",
            "cameraZ": "",
            "formula": "$$\\frac{\\sqrt{\\left(Ac_l.x-Prn.x\\right)^2+\\left(Ac_l.y-Prn.y\\right)^2+\\left(Ac_l.z-Prn.z\\right)^2}}{\\sqrt{\\left(Prn.x-N.x\\right)^2+\\left(Prn.y-N.y\\right)^2+\\left(Prn.z-N.z\\right)^2}}$$"
        },
        {
            "id": "Nasal_Width-Length_Ratio",
            "name": "Nasal Width-Length Ratio",
            "imageFile": "measurement_ratio_nasal_width_length_ratio-frontal.png",
            "description": "The alar base width divided by the nasal bridge length.",
            "type": "Ratios",
            "group": "Ratios",
            "list": "Y",
            "references": "(56, 90)",
            "usedFeatures": [
                "Alare/Alar_Flare_left",
                "Alare/Alar_Flare_right",
                "Pronasale/Tip",
                "Nasion/Radix"
            ],
            "value": "0.54",
            "cameraX": "",
            "cameraY": "",
            "cameraZ": "",
            "formula": "$$\\frac{Interalar Distance}{Nasal Bridge Length}$$ $$\\frac{\\sqrt{\\left(Al_r.x-Al_l.x\\right)^2+\\left(Al_r.y-Al_l.y\\right)^2+\\left(Al_r.z-Al_l.z\\right)^2}}{\\sqrt{\\left(Prn.x-N.x\\right)^2+\\left(Prn.y-N.y\\right)^2+\\left(Prn.z-N.z\\right)^2}}$$"
        }
    ]
}